simdkalman/__init__.py
simdkalman/kalmanfilter.py
simdkalman/primitives.py
simdkalman-1.0.3.dist-info/LICENSE.txt
simdkalman-1.0.3.dist-info/METADATA
simdkalman-1.0.3.dist-info/WHEEL
simdkalman-1.0.3.dist-info/top_level.txt
simdkalman-1.0.3.dist-info/RECORD
